styletransfer/__about__.py
styletransfer/__init__.py
styletransfer/exceptions.py
styletransfer/model.py
styletransfer/wrapper.py
styletransfer-0.8.2.dist-info/LICENSE
styletransfer-0.8.2.dist-info/METADATA
styletransfer-0.8.2.dist-info/WHEEL
styletransfer-0.8.2.dist-info/top_level.txt
styletransfer-0.8.2.dist-info/RECORD
